cryptobulb/__init__.py
cryptobulb-0.1.0.dist-info/METADATA
cryptobulb-0.1.0.dist-info/WHEEL
cryptobulb-0.1.0.dist-info/top_level.txt
cryptobulb-0.1.0.dist-info/RECORD
