Metadata-Version: 2.1
Name: cryptobulb
Version: 0.1.0
Summary: A library for single layer perceptron
Home-page: https://github.com/your-username/cryptobulb
Author: Your Name
Author-email: your.email@example.com
License: MIT
Classifier: Programming Language :: Python :: 3
Classifier: License :: OSI Approved :: MIT License
Classifier: Topic :: Scientific/Engineering :: Artificial Intelligence
